bambooai/__init__.py
bambooai/bambooai.py
bambooai/code_executor.py
bambooai/context_retrieval.py
bambooai/executor_client.py
bambooai/google_search.py
bambooai/log_manager.py
bambooai/output_manager.py
bambooai/qa_retrieval.py
bambooai/storage_manager.py
bambooai/template_formatting.py
bambooai/utils.py
bambooai/web_output_manager.py
bambooai/messages/__init__.py
bambooai/messages/default_prompts.yaml
bambooai/messages/message_manager.py
bambooai/messages/prompts.py
bambooai/messages/reg_ex.py
bambooai/messages/tools_definition.py
bambooai/models/__init__.py
bambooai/models/anthropic_models.py
bambooai/models/deepseek_models.py
bambooai/models/gemini_models.py
bambooai/models/gemini_models_openai.py
bambooai/models/groq_models.py
bambooai/models/local_models.py
bambooai/models/mistral_models.py
bambooai/models/ollama_models.py
bambooai/models/openai_models.py
bambooai/models/openrouter_models.py
bambooai/models/vllm_models.py
bambooai-0.4.24.dist-info/licenses/LICENSE
web_app/__init__.py
web_app/app.py
web_app/code_executor_api.py
bambooai-0.4.24.dist-info/METADATA
bambooai-0.4.24.dist-info/WHEEL
bambooai-0.4.24.dist-info/top_level.txt
bambooai-0.4.24.dist-info/RECORD
