Metadata-Version: 2.4
Name: bambooai
Version: 0.4.24
Summary: A lightweight library for working with pandas dataframes using natural language queries
Author: Palo Galko
Classifier: Development Status :: 3 - Alpha
Classifier: License :: OSI Approved :: MIT License
Classifier: Programming Language :: Python :: 3
Requires-Python: >=3.10
License-File: LICENSE
Requires-Dist: openai
Requires-Dist: tiktoken
Requires-Dist: pandas
Requires-Dist: numpy
Requires-Dist: pyarrow
Requires-Dist: matplotlib
Requires-Dist: seaborn
Requires-Dist: plotly==6.0.1
Requires-Dist: termcolor
Requires-Dist: newspaper3k
Requires-Dist: pinecone==6.0.2
Requires-Dist: selenium
Requires-Dist: google-generativeai
Requires-Dist: google-genai
Requires-Dist: groq
Requires-Dist: ollama
Requires-Dist: anthropic
Requires-Dist: mistralai
Requires-Dist: flask
Requires-Dist: ipython
Requires-Dist: nbformat
Requires-Dist: python-dotenv
Requires-Dist: lxml_html_clean
Requires-Dist: gunicorn
Requires-Dist: google-cloud-storage
Requires-Dist: statsmodels
Requires-Dist: scipy
Requires-Dist: scikit-learn
Requires-Dist: geopandas
Requires-Dist: yfinance
Requires-Dist: sweatstack
Dynamic: author
Dynamic: classifier
Dynamic: description
Dynamic: description-content-type
Dynamic: license-file
Dynamic: requires-dist
Dynamic: requires-python
Dynamic: summary
